rosetta_cipher/__init__.py
rosetta_cipher/adjectives.py
rosetta_cipher/cipher.py
rosetta_cipher/cli.py
rosetta_cipher/scientists.py
rosetta_cipher/web.py
rosetta_cipher/wsgi.py
rosetta_cipher-0.1.0.dist-info/entry_points.txt
rosetta_cipher-0.1.0.dist-info/LICENSE
rosetta_cipher-0.1.0.dist-info/WHEEL
rosetta_cipher-0.1.0.dist-info/METADATA
rosetta_cipher-0.1.0.dist-info/RECORD
